setup.py
analyzer/__init__.py
analyzer.egg-info/PKG-INFO
analyzer.egg-info/SOURCES.txt
analyzer.egg-info/dependency_links.txt
analyzer.egg-info/requires.txt
analyzer.egg-info/top_level.txt