Metadata-Version: 1.1
Name: analyzer
Version: 0.0.1
Summary: python project for finance: realtime data collection, analyze, algorithmic trading
Home-page: https://github.com/llazzaro/analyzer
Author: Leonardo Lazzaro (original author Pan)
Author-email: lazzarleonardo@gmail.com
License: MIT
Keywords: python,Finance,Algorithm,Trading,Realtime,QuantLib,pydispather
Platform: UNKNOWN
Classifier: Intended Audience :: Developers
Classifier: License :: OSI Approved :: MIT License
